{"big_bubbler":{"name":"Big Bubbler","img":"Big_Bubbler"},"booyah_bomb":{"name":"Booyah Bomb","img":"Booyah_Bomb"},"crab_tank":{"name":"Crab Tank","img":"Crab_Tank"},"ink_storm":{"name":"Ink Storm","img":"Ink_Storm"},"ink_vac":{"name":"Ink Vac","img":"Ink_Vac"},"inkjet":{"name":"Inkjet","img":"Inkjet"},"killer_wail_5.1":{"name":"Killer Wail 5.1","img":"Killer_Wail_5.1"},"reefslider":{"name":"Reefslider","img":"Reefslider"},"splashdown":{"name":"Splashdown","img":"Splashdown"},"tacticooler":{"name":"Tacticooler","img":"Tacticooler"},"tenta_missiles":{"name":"Tenta Missiles","img":"Tenta_Missiles"},"triple_inkstrike":{"name":"Triple Inkstrike","img":"Triple_Inkstrike"},"trizooka":{"name":"Trizooka","img":"Trizooka"},"ultra_stamp":{"name":"Ultra Stamp","img":"Ultra_Stamp"},"wave_breaker":{"name":"Wave Breaker","img":"Wave_Breaker"},"zipcaster":{"name":"Zipcaster","img":"Zipcaster"},"kraken_royale":{"name":"Kraken Royale","img":"Kraken_Royale"},"super_chump":{"name":"Super Chump","img":"Super_Chump"},"splattercolor_screen":{"name":"Splattercolor Screen","img":"Splattercolor_Screen"},"triple_splashdown":{"name":"Triple Splashdown","img":"Triple_Splashdown"}}